pypkgs_rissangs/__init__.py
pypkgs_rissangs/pypkgs_rissangs.py
pypkgs_rissangs-1.1.5.dist-info/LICENSE
pypkgs_rissangs-1.1.5.dist-info/WHEEL
pypkgs_rissangs-1.1.5.dist-info/METADATA
pypkgs_rissangs-1.1.5.dist-info/RECORD
